extension/__init__.py
extension/extension.py
lib/__init__.py
lib/db.py
lib/helpers.py
lib/lib/__init__.py
lib/lib/db.py
lib/lib/helpers.py
lib/lib/settings.py
lib/pyproject.toml
lib/settings.py
lnbits_extension-0.10.8.2.dist-info/METADATA
lnbits_extension-0.10.8.2.dist-info/WHEEL
lnbits_extension-0.10.8.2.dist-info/entry_points.txt
lnbits_extension-0.10.8.2.dist-info/RECORD
